README.rst
setup.py
tvrage/__init__.py
tvrage/api.py
tvrage/exceptions.py
tvrage/feeds.py
tvrage/quickinfo.py
tvrage/util.py
tvrampage.egg-info/PKG-INFO
tvrampage.egg-info/SOURCES.txt
tvrampage.egg-info/dependency_links.txt
tvrampage.egg-info/requires.txt
tvrampage.egg-info/top_level.txt