Metadata-Version: 1.1
Name: tvrampage
Version: 1.0.2
Summary: python client for the tvrage.com XML API
Home-page: https://github.com/ckreutzer/python-tvrage
Author: Christian Kreutzer
Author-email: herr.kreutzer@gmail.com
License: BSD
Platform: UNKNOWN
Classifier: Development Status :: 4 - Beta
Classifier: Intended Audience :: Developers
Classifier: License :: OSI Approved :: BSD License
Classifier: Topic :: Software Development :: Libraries :: Python Modules
Classifier: Programming Language :: Python
Classifier: Operating System :: OS Independent
